{
  "object": "page",
  "id": "dffa6fc2-7f09-4640-9ab0-a6e26309140b",
  "created_time": "2023-01-27T13:59:00.000Z",
  "last_edited_time": "2023-03-17T16:08:00.000Z",
  "created_by": {
    "object": "user",
    "id": "95fc0174-8fc6-4114-8e45-f67eacd99f07"
  },
  "last_edited_by": {
    "object": "user",
    "id": "95fc0174-8fc6-4114-8e45-f67eacd99f07"
  },
  "cover": {},
  "icon": null,
  "parent": {
    "type": "database_id",
    "database_id": "be65d799-9e98-4426-86a6-72072991e27b"
  },
  "archived": false,
  "properties": {
    "HashTags": {
      "id": "Hhkx",
      "type": "multi_select",
      "multi_select": []
    },
    "생성 일시": {
      "id": "J%7C%3BZ",
      "type": "created_time",
      "created_time": "2023-01-27T13:59:00.000Z"
    },
    "Slug": {
      "id": "S%3A%7B%3E",
      "type": "rich_text",
      "rich_rich_text": [
        {
          "type": "text",
          "text": {
            "content": "asdf",
            "link": null
          },
          "annotations": {
            "bold": false,
            "italic": false,
            "strikethrough": false,
            "underline": false,
            "code": false,
            "color": "default"
          },
          "plain_text": "asdf",
          "href": null
        }
      ]
    },
    "텍스트": {
      "id": "q%3CHh",
      "type": "rich_text",
      "rich_rich_text": []
    },
    "Description": {
      "id": "qTV%3E",
      "type": "rich_text",
      "rich_rich_text": []
    },
    "Status": {
      "id": "vu%7C%3B",
      "type": "select",
      "select": {
        "id": "|QrX",
        "name": "Publishable",
        "color": "green"
      }
    },
    "Name": {
      "id": "title",
      "type": "title",
      "title": [
        {
          "type": "text",
          "text": {
            "content": "Test",
            "link": null
          },
          "annotations": {
            "bold": false,
            "italic": false,
            "strikethrough": false,
            "underline": false,
            "code": false,
            "color": "default"
          },
          "plain_text": "Test",
          "href": null
        }
      ]
    }
  },
  "url": "https://www.notion.so/Test-dffa6fc27f0946409ab0a6e26309140b",
  "blocks": [
    {
      "object": "block",
      "id": "eeacc1d6-d8d8-4d3a-a57f-6d2a30403074",
      "parent": {
        "type": "page_id",
        "page_id": "dffa6fc2-7f09-4640-9ab0-a6e26309140b"
      },
      "created_time": "2023-02-17T05:51:00.000Z",
      "last_edited_time": "2023-03-17T16:06:00.000Z",
      "created_by": {
        "object": "user",
        "id": "95fc0174-8fc6-4114-8e45-f67eacd99f07"
      },
      "last_edited_by": {
        "object": "user",
        "id": "95fc0174-8fc6-4114-8e45-f67eacd99f07"
      },
      "has_children": false,
      "archived": false,
      "type": "paragraph",
      "paragraph": {
        "color": "gray_background",
        "rich_text": []
      }
    },
    {
      "object": "block",
      "id": "f3eab6d3-fa21-4f62-b586-9fffc93c3fdd",
      "parent": {
        "type": "page_id",
        "page_id": "dffa6fc2-7f09-4640-9ab0-a6e26309140b"
      },
      "created_time": "2023-03-17T16:06:00.000Z",
      "last_edited_time": "2023-03-17T16:08:00.000Z",
      "created_by": {
        "object": "user",
        "id": "95fc0174-8fc6-4114-8e45-f67eacd99f07"
      },
      "last_edited_by": {
        "object": "user",
        "id": "95fc0174-8fc6-4114-8e45-f67eacd99f07"
      },
      "has_children": false,
      "archived": false,
      "type": "video",
      "video": {
        "caption": [],
        "type": "external",
        "external": {
          "url": "https://www.youtube.com/watch?v=S92KX8-Hmlc"
        }
      }
    },
    {
      "object": "block",
      "id": "31e85e09-1ffd-4754-825b-bf92ae63d5af",
      "parent": {
        "type": "page_id",
        "page_id": "dffa6fc2-7f09-4640-9ab0-a6e26309140b"
      },
      "created_time": "2023-02-17T05:51:00.000Z",
      "last_edited_time": "2023-03-17T16:06:00.000Z",
      "created_by": {
        "object": "user",
        "id": "95fc0174-8fc6-4114-8e45-f67eacd99f07"
      },
      "last_edited_by": {
        "object": "user",
        "id": "95fc0174-8fc6-4114-8e45-f67eacd99f07"
      },
      "has_children": false,
      "archived": false,
      "type": "paragraph",
      "paragraph": {
        "color": "gray_background",
        "rich_text": []
      }
    }
  ]
}
